yo_fabric
