Metadata-Version: 1.1
Name: yo-fabric
Version: 0.1.3
Summary: Default fabric tasks for you python project (Simplified version of Fabricator).
Home-page: https://github.com/DigitalDemiurge/yo-fabric
Author: Vitaliy Korobkin
Author-email: root@digitaldemiurge.me
License: MIT license
Platform: UNKNOWN
Classifier: Development Status :: 4 - Beta
Classifier: Environment :: Console
Classifier: License :: OSI Approved :: MIT License
Classifier: Programming Language :: Python
Classifier: Programming Language :: Python :: 2
Classifier: Programming Language :: Python :: 2.6
Classifier: Programming Language :: Python :: 2.7
Classifier: Topic :: Software Development :: Libraries :: Python Modules
Requires: Fabric (>= 1.4)
